{
    "websiteAnalytic": [
        {
            "name": "10/12",
            "visits": 100,
            "clicks": 60,
            "sales": 20
        },
        {
            "name": "11/12",
            "visits": 120,
            "clicks": 80,
            "sales": 40
        },
        {
            "name": "12/12",
            "visits": 90,
            "clicks": 70,
            "sales": 30
        },
        {
            "name": "13/12",
            "visits": 170,
            "clicks": 110,
            "sales": 70
        },
        {
            "name": "14/12",
            "visits": 130,
            "clicks": 80,
            "sales": 40
        },
        {
            "name": "15/12",
            "visits": 160,
            "clicks": 100,
            "sales": 60
        },
        {
            "name": "16/12",
            "visits": 140,
            "clicks": 90,
            "sales": 50
        },
        {
            "name": "17/12",
            "visits": 240,
            "clicks": 180,
            "sales": 140
        },
        {
            "name": "18/12",
            "visits": 220,
            "clicks": 160,
            "sales": 120
        },
        {
            "name": "19/12",
            "visits": 180,
            "clicks": 140,
            "sales": 100
        },
        {
            "name": "20/12",
            "visits": 270,
            "clicks": 200,
            "sales": 140
        },
        {
            "name": "21/12",
            "visits": 280,
            "clicks": 220,
            "sales": 180
        },
        {
            "name": "22/12",
            "visits": 375,
            "clicks": 275,
            "sales": 220
        }
    ],
    "balance": [
        {
            "name": "7/12",
            "pv": 280
        },
        {
            "name": "8/12",
            "pv": 200
        },
        {
            "name": "9/12",
            "pv": 220
        },
        {
            "name": "10/12",
            "pv": 180
        },
        {
            "name": "11/12",
            "pv": 270
        },
        {
            "name": "12/12",
            "pv": 250
        },
        {
            "name": "13/12",
            "pv": 70
        },
        {
            "name": "14/12",
            "pv": 90
        },
        {
            "name": "15/12",
            "pv": 200
        },
        {
            "name": "16/12",
            "pv": 150
        },
        {
            "name": "17/12",
            "pv": 160
        },
        {
            "name": "18/12",
            "pv": 100
        },
        {
            "name": "19/12",
            "pv": 150
        },
        {
            "name": "20/12",
            "pv": 100
        },
        {
            "name": "21/12",
            "pv": 50
        }
    ],
    "frameworkUsage": [
        [
            {
                "x": 5.4,
                "y": 170,
                "z": 130
            },
            {
                "x": 5.4,
                "y": 100,
                "z": 90
            },
            {
                "x": 5.7,
                "y": 110,
                "z": 80
            },
            {
                "x": 5.9,
                "y": 150,
                "z": 120
            },
            {
                "x": 6,
                "y": 200,
                "z": 210
            },
            {
                "x": 6.3,
                "y": 170,
                "z": 60
            },
            {
                "x": 5.7,
                "y": 140,
                "z": 40
            },
            {
                "x": 5.9,
                "y": 130,
                "z": 70
            },
            {
                "x": 7,
                "y": 150,
                "z": 150
            },
            {
                "x": 8,
                "y": 120,
                "z": 190
            },
            {
                "x": 9,
                "y": 170,
                "z": 120
            },
            {
                "x": 10,
                "y": 190,
                "z": 120
            },
            {
                "x": 11,
                "y": 220,
                "z": 210
            },
            {
                "x": 12,
                "y": 170,
                "z": 120
            },
            {
                "x": 13,
                "y": 230,
                "z": 20
            }
        ],
        [
            {
                "x": 14,
                "y": 290,
                "z": 232
            },
            {
                "x": 13,
                "y": 190,
                "z": 233
            },
            {
                "x": 20,
                "y": 220,
                "z": 121
            },
            {
                "x": 21,
                "y": 350,
                "z": 189
            },
            {
                "x": 21.5,
                "y": 290,
                "z": 34
            },
            {
                "x": 22,
                "y": 220,
                "z": 67
            },
            {
                "x": 23,
                "y": 140,
                "z": 210
            },
            {
                "x": 19,
                "y": 400,
                "z": 120
            },
            {
                "x": 20,
                "y": 200,
                "z": 132
            },
            {
                "x": 22,
                "y": 90,
                "z": 120
            },
            {
                "x": 20,
                "y": 120,
                "z": 40
            }
        ],
        [
            {
                "x": 55.4,
                "y": 170,
                "z": 203
            },
            {
                "x": 143,
                "y": 100,
                "z": 121
            },
            {
                "x": 5.7,
                "y": 110,
                "z": 156
            },
            {
                "x": 5.9,
                "y": 150,
                "z": 231
            },
            {
                "x": 6,
                "y": 200,
                "z": 353
            },
            {
                "x": 6.3,
                "y": 170,
                "z": 432
            },
            {
                "x": 5.7,
                "y": 140,
                "z": 756
            },
            {
                "x": 5.9,
                "y": 130,
                "z": 346
            },
            {
                "x": 7,
                "y": 150,
                "z": 654
            },
            {
                "x": 8,
                "y": 120,
                "z": 657
            },
            {
                "x": 9,
                "y": 170,
                "z": 456
            },
            {
                "x": 10,
                "y": 190,
                "z": 787
            },
            {
                "x": 43,
                "y": 45,
                "z": 43
            },
            {
                "x": 765,
                "y": 324,
                "z": 23
            },
            {
                "x": 43,
                "y": 32,
                "z": 76
            }
        ]
    ],
    "turnover": [
        {
            "name": "7/12",
            "apple": 90,
            "samsung": 85,
            "sony": 80
        },
        {
            "name": "8/12",
            "apple": 120,
            "samsung": 130,
            "sony": 110
        },
        {
            "name": "9/12",
            "apple": 55,
            "samsung": 76,
            "sony": 80
        },
        {
            "name": "10/12",
            "apple": 100,
            "samsung": 80,
            "sony": 89
        },
        {
            "name": "11/12",
            "apple": 80,
            "samsung": 105,
            "sony": 95
        },
        {
            "name": "12/12",
            "apple": 125,
            "samsung": 145,
            "sony": 120
        },
        {
            "name": "13/12",
            "apple": 175,
            "samsung": 157,
            "sony": 140
        },
        {
            "name": "14/12",
            "apple": 70,
            "samsung": 89,
            "sony": 67
        },
        {
            "name": "15/12",
            "apple": 88,
            "samsung": 90,
            "sony": 100
        }
    ],
    "mobileComparison": [
        {
            "category": "Camera",
            "samsung": 65,
            "iphon": 41
        },
        {
            "category": "Battery",
            "samsung": 46,
            "iphon": 64
        },
        {
            "category": "Screen",
            "samsung": 42,
            "iphon": 81
        },
        {
            "category": "Speaker",
            "samsung": 25,
            "iphon": 60
        },
        {
            "category": "Software",
            "samsung": 58,
            "iphon": 42
        },
        {
            "category": "CPU",
            "samsung": 63,
            "iphon": 42
        },
        {
            "category": "GPU",
            "samsung": 76,
            "iphon": 33
        },
        {
            "category": "Price",
            "samsung": 43,
            "iphon": 23
        }
    ],
    "expense": [
        {
            "name": "R&D",
            "value": 42
        },
        {
            "name": "Hiring",
            "value": 24
        },
        {
            "name": "Networking",
            "value": 7
        },
        {
            "name": "Operational",
            "value": 43
        }
    ]
    
}
